label_studio_sso/__init__.py
label_studio_sso/apps.py
label_studio_sso/authentication.py
label_studio_sso/backends.py
label_studio_sso/middleware.py
label_studio_sso/urls.py
label_studio_sso/views.py
label_studio_sso-6.0.8.dist-info/licenses/LICENSE
tests/__init__.py
tests/conftest.py
tests/test_backends.py
tests/test_integration.py
tests/test_middleware.py
tests/test_settings.py
tests/test_simple.py
label_studio_sso-6.0.8.dist-info/METADATA
label_studio_sso-6.0.8.dist-info/WHEEL
label_studio_sso-6.0.8.dist-info/top_level.txt
label_studio_sso-6.0.8.dist-info/RECORD
