Metadata-Version: 2.4
Name: label-studio-sso
Version: 6.0.8
Summary: Native JWT authentication for Label Studio OSS - simple and secure SSO integration
Home-page: https://github.com/aidoop/label-studio-sso
Author: AIdoop Team
Author-email: AIdoop Team <admin@aidoop.com>
License: MIT
Project-URL: Homepage, https://github.com/aidoop/label-studio-sso
Project-URL: Documentation, https://github.com/aidoop/label-studio-sso/blob/main/README.md
Project-URL: Repository, https://github.com/aidoop/label-studio-sso
Project-URL: Issues, https://github.com/aidoop/label-studio-sso/issues
Keywords: label-studio,label-studio-oss,sso,jwt,authentication,django,native-jwt,open-source,oss
Classifier: Development Status :: 5 - Production/Stable
Classifier: Intended Audience :: Developers
Classifier: License :: OSI Approved :: MIT License
Classifier: Operating System :: OS Independent
Classifier: Programming Language :: Python :: 3
Classifier: Programming Language :: Python :: 3.8
Classifier: Programming Language :: Python :: 3.9
Classifier: Programming Language :: Python :: 3.10
Classifier: Programming Language :: Python :: 3.11
Classifier: Framework :: Django
Requires-Python: >=3.8
License-File: LICENSE
Requires-Dist: Django>=3.2
Requires-Dist: PyJWT>=2.0.0
Requires-Dist: requests>=2.25.0
Provides-Extra: dev
Requires-Dist: pytest>=7.0; extra == "dev"
Requires-Dist: pytest-django>=4.5; extra == "dev"
Requires-Dist: black>=22.0; extra == "dev"
Requires-Dist: flake8>=4.0; extra == "dev"
Dynamic: author
Dynamic: home-page
Dynamic: license-file
Dynamic: requires-python
